topsis_assignment/__init__.py
topsis_assignment/__main__.py
Topsis_Royal_102016082-2.0.dist-info/METADATA
Topsis_Royal_102016082-2.0.dist-info/WHEEL
Topsis_Royal_102016082-2.0.dist-info/entry_points.txt
Topsis_Royal_102016082-2.0.dist-info/top_level.txt
Topsis_Royal_102016082-2.0.dist-info/RECORD
