Metadata-Version: 2.1
Name: Topsis-Royal-102016082
Version: 2.0
Summary: Topsis Assignment
Author: Royal Garg
Author-email: royalgarg36@gmail.com
License: MIT
Classifier: License :: OSI Approved :: MIT License
Classifier: Programming Language :: Python :: 3.6
Classifier: Programming Language :: Python :: 3.7
Classifier: Programming Language :: Python :: 3.8
